{
	"configurations" : 
	[
		{
			"directories" : 
			[
				{
					"build" : ".",
					"jsonFile" : "directory-.-Debug-f5ebdc15457944623624.json",
					"minimumCMakeVersion" : 
					{
						"string" : "3.20"
					},
					"projectIndex" : 0,
					"source" : ".",
					"targetIndexes" : 
					[
						0,
						1,
						2,
						3
					]
				}
			],
			"name" : "Debug",
			"projects" : 
			[
				{
					"directoryIndexes" : 
					[
						0
					],
					"name" : "UniLabs",
					"targetIndexes" : 
					[
						0,
						1,
						2,
						3
					]
				}
			],
			"targets" : 
			[
				{
					"directoryIndex" : 0,
					"id" : "lab::@6890427a1f51a3e7e1df",
					"jsonFile" : "target-lab-Debug-baece7dc9ac91be79e1e.json",
					"name" : "lab",
					"projectIndex" : 0
				},
				{
					"directoryIndex" : 0,
					"id" : "lab1::@6890427a1f51a3e7e1df",
					"jsonFile" : "target-lab1-Debug-093606bdb3c33f96a755.json",
					"name" : "lab1",
					"projectIndex" : 0
				},
				{
					"directoryIndex" : 0,
					"id" : "lab2::@6890427a1f51a3e7e1df",
					"jsonFile" : "target-lab2-Debug-2c08c485d7162f5b1e90.json",
					"name" : "lab2",
					"projectIndex" : 0
				},
				{
					"directoryIndex" : 0,
					"id" : "run::@6890427a1f51a3e7e1df",
					"jsonFile" : "target-run-Debug-ea8477120b6a0161536b.json",
					"name" : "run",
					"projectIndex" : 0
				}
			]
		}
	],
	"kind" : "codemodel",
	"paths" : 
	{
		"build" : "/home/ethan/CS120_Labs/out/build/GCC 13.3.0 x86_64-linux-gnu",
		"source" : "/home/ethan/CS120_Labs"
	},
	"version" : 
	{
		"major" : 2,
		"minor" : 6
	}
}
